LICENSE
README.md
setup.py
examples/__init__.py
examples/example1.py
zalo_official/APIConfig.py
zalo_official/APIException.py
zalo_official/ApiBaseClient.py
zalo_official/__init__.py
zalo_official/app/AppClient.py
zalo_official/app/AppInfo.py
zalo_official/app/__init__.py
zalo_official/article/ArticleClient.py
zalo_official/article/__init__.py
zalo_official/oa/OaClient.py
zalo_official/oa/OaInfo.py
zalo_official/oa/OaOnbehalf.py
zalo_official/oa/__init__.py
zalo_official/store/StoreClient.py
zalo_official/store/StoreOnbehalfClient.py
zalo_official/store/__init__.py
zalo_official/test/__init__.py
zalo_official/test/unit.py
zalo_official/utils/MacUtils.py
zalo_official/utils/__init__.py
zalo_official_sdk.egg-info/PKG-INFO
zalo_official_sdk.egg-info/SOURCES.txt
zalo_official_sdk.egg-info/dependency_links.txt
zalo_official_sdk.egg-info/top_level.txt