Metadata-Version: 2.1
Name: zalo-official-sdk
Version: 1.0.1
Summary: Zalo Official SDK
Home-page: https://github.com/hieutt39/python-zalo-official-sdk
Author: Hieutt39
Author-email: 
License: GPL-2.0 License
Keywords: zalo,sdk
Platform: UNKNOWN
Requires-Python: >=3.6
License-File: LICENSE
